[
    {
        "trainer/global_step": 49,
        "_step": 0,
        "_runtime": 57.843752776,
        "lr-SGD": 1e-05,
        "_timestamp": 1736357928.6782,
        "epoch": NaN,
        "loss/train_step": NaN,
        "acc/val": NaN,
        "loss/val": NaN,
        "acc/train_epoch": NaN,
        "loss/train_epoch": NaN,
        "acc/test": NaN,
        "loss/test": NaN
    },
    {
        "trainer/global_step": 49,
        "_step": 1,
        "_runtime": 57.954992799,
        "lr-SGD": NaN,
        "_timestamp": 1736357928.7892084,
        "epoch": 0.0,
        "loss/train_step": 0.0270241592079401,
        "acc/val": NaN,
        "loss/val": NaN,
        "acc/train_epoch": NaN,
        "loss/train_epoch": NaN,
        "acc/test": NaN,
        "loss/test": NaN
    },
    {
        "trainer/global_step": 99,
        "_step": 2,
        "_runtime": 63.808893132,
        "lr-SGD": 1e-05,
        "_timestamp": 1736357934.6433375,
        "epoch": NaN,
        "loss/train_step": NaN,
        "acc/val": NaN,
        "loss/val": NaN,
        "acc/train_epoch": NaN,
        "loss/train_epoch": NaN,
        "acc/test": NaN,
        "loss/test": NaN
    },
    {
        "trainer/global_step": 99,
        "_step": 3,
        "_runtime": 63.919623309,
        "lr-SGD": NaN,
        "_timestamp": 1736357934.7542489,
        "epoch": 0.0,
        "loss/train_step": 0.03356384113430977,
        "acc/val": NaN,
        "loss/val": NaN,
        "acc/train_epoch": NaN,
        "loss/train_epoch": NaN,
        "acc/test": NaN,
        "loss/test": NaN
    },
    {
        "trainer/global_step": 140,
        "_step": 4,
        "_runtime": 71.802194694,
        "lr-SGD": NaN,
        "_timestamp": 1736357942.6367695,
        "epoch": 0.0,
        "loss/train_step": NaN,
        "acc/val": 0.9700000286102295,
        "loss/val": 0.10898783057928085,
        "acc/train_epoch": NaN,
        "loss/train_epoch": NaN,
        "acc/test": NaN,
        "loss/test": NaN
    },
    {
        "trainer/global_step": 140,
        "_step": 5,
        "_runtime": 90.939143783,
        "lr-SGD": NaN,
        "_timestamp": 1736357961.77373,
        "epoch": 0.0,
        "loss/train_step": NaN,
        "acc/val": NaN,
        "loss/val": NaN,
        "acc/train_epoch": 0.9808889031410217,
        "loss/train_epoch": 0.07384179532527924,
        "acc/test": NaN,
        "loss/test": NaN
    },
    {
        "trainer/global_step": 149,
        "_step": 6,
        "_runtime": 94.382804651,
        "lr-SGD": 1e-05,
        "_timestamp": 1736357965.217269,
        "epoch": NaN,
        "loss/train_step": NaN,
        "acc/val": NaN,
        "loss/val": NaN,
        "acc/train_epoch": NaN,
        "loss/train_epoch": NaN,
        "acc/test": NaN,
        "loss/test": NaN
    },
    {
        "trainer/global_step": 149,
        "_step": 7,
        "_runtime": 94.495605669,
        "lr-SGD": NaN,
        "_timestamp": 1736357965.3298264,
        "epoch": 1.0,
        "loss/train_step": 0.142131045460701,
        "acc/val": NaN,
        "loss/val": NaN,
        "acc/train_epoch": NaN,
        "loss/train_epoch": NaN,
        "acc/test": NaN,
        "loss/test": NaN
    },
    {
        "trainer/global_step": 199,
        "_step": 8,
        "_runtime": 100.384472842,
        "lr-SGD": 1e-05,
        "_timestamp": 1736357971.2190166,
        "epoch": NaN,
        "loss/train_step": NaN,
        "acc/val": NaN,
        "loss/val": NaN,
        "acc/train_epoch": NaN,
        "loss/train_epoch": NaN,
        "acc/test": NaN,
        "loss/test": NaN
    },
    {
        "trainer/global_step": 199,
        "_step": 9,
        "_runtime": 100.493691084,
        "lr-SGD": NaN,
        "_timestamp": 1736357971.3284132,
        "epoch": 1.0,
        "loss/train_step": 0.1190684586763382,
        "acc/val": NaN,
        "loss/val": NaN,
        "acc/train_epoch": NaN,
        "loss/train_epoch": NaN,
        "acc/test": NaN,
        "loss/test": NaN
    },
    {
        "trainer/global_step": 249,
        "_step": 10,
        "_runtime": 106.395927235,
        "lr-SGD": 1e-05,
        "_timestamp": 1736357977.2305958,
        "epoch": NaN,
        "loss/train_step": NaN,
        "acc/val": NaN,
        "loss/val": NaN,
        "acc/train_epoch": NaN,
        "loss/train_epoch": NaN,
        "acc/test": NaN,
        "loss/test": NaN
    },
    {
        "trainer/global_step": 249,
        "_step": 11,
        "_runtime": 106.509930345,
        "lr-SGD": NaN,
        "_timestamp": 1736357977.343504,
        "epoch": 1.0,
        "loss/train_step": 0.02502845600247383,
        "acc/val": NaN,
        "loss/val": NaN,
        "acc/train_epoch": NaN,
        "loss/train_epoch": NaN,
        "acc/test": NaN,
        "loss/test": NaN
    },
    {
        "trainer/global_step": 281,
        "_step": 12,
        "_runtime": 113.448602664,
        "lr-SGD": NaN,
        "_timestamp": 1736357984.283217,
        "epoch": 1.0,
        "loss/train_step": NaN,
        "acc/val": 0.9760000109672546,
        "loss/val": 0.094425268471241,
        "acc/train_epoch": NaN,
        "loss/train_epoch": NaN,
        "acc/test": NaN,
        "loss/test": NaN
    },
    {
        "trainer/global_step": 281,
        "_step": 13,
        "_runtime": 132.891735278,
        "lr-SGD": NaN,
        "_timestamp": 1736358003.7262528,
        "epoch": 1.0,
        "loss/train_step": NaN,
        "acc/val": NaN,
        "loss/val": NaN,
        "acc/train_epoch": 0.9853333234786987,
        "loss/train_epoch": 0.06684289872646332,
        "acc/test": NaN,
        "loss/test": NaN
    },
    {
        "trainer/global_step": 299,
        "_step": 14,
        "_runtime": 137.708425248,
        "lr-SGD": 1e-05,
        "_timestamp": 1736358008.5425658,
        "epoch": NaN,
        "loss/train_step": NaN,
        "acc/val": NaN,
        "loss/val": NaN,
        "acc/train_epoch": NaN,
        "loss/train_epoch": NaN,
        "acc/test": NaN,
        "loss/test": NaN
    },
    {
        "trainer/global_step": 299,
        "_step": 15,
        "_runtime": 137.819466897,
        "lr-SGD": NaN,
        "_timestamp": 1736358008.6541615,
        "epoch": 2.0,
        "loss/train_step": 0.03455014526844025,
        "acc/val": NaN,
        "loss/val": NaN,
        "acc/train_epoch": NaN,
        "loss/train_epoch": NaN,
        "acc/test": NaN,
        "loss/test": NaN
    },
    {
        "trainer/global_step": 349,
        "_step": 16,
        "_runtime": 143.707282763,
        "lr-SGD": 1e-05,
        "_timestamp": 1736358014.5420532,
        "epoch": NaN,
        "loss/train_step": NaN,
        "acc/val": NaN,
        "loss/val": NaN,
        "acc/train_epoch": NaN,
        "loss/train_epoch": NaN,
        "acc/test": NaN,
        "loss/test": NaN
    },
    {
        "trainer/global_step": 349,
        "_step": 17,
        "_runtime": 143.815793719,
        "lr-SGD": NaN,
        "_timestamp": 1736358014.6506119,
        "epoch": 2.0,
        "loss/train_step": 0.1637553721666336,
        "acc/val": NaN,
        "loss/val": NaN,
        "acc/train_epoch": NaN,
        "loss/train_epoch": NaN,
        "acc/test": NaN,
        "loss/test": NaN
    },
    {
        "trainer/global_step": 399,
        "_step": 18,
        "_runtime": 149.670389038,
        "lr-SGD": 1e-05,
        "_timestamp": 1736358020.5051267,
        "epoch": NaN,
        "loss/train_step": NaN,
        "acc/val": NaN,
        "loss/val": NaN,
        "acc/train_epoch": NaN,
        "loss/train_epoch": NaN,
        "acc/test": NaN,
        "loss/test": NaN
    },
    {
        "trainer/global_step": 399,
        "_step": 19,
        "_runtime": 149.780096335,
        "lr-SGD": NaN,
        "_timestamp": 1736358020.6147609,
        "epoch": 2.0,
        "loss/train_step": 0.0804523378610611,
        "acc/val": NaN,
        "loss/val": NaN,
        "acc/train_epoch": NaN,
        "loss/train_epoch": NaN,
        "acc/test": NaN,
        "loss/test": NaN
    },
    {
        "trainer/global_step": 422,
        "_step": 20,
        "_runtime": 155.337787814,
        "lr-SGD": NaN,
        "_timestamp": 1736358026.1723902,
        "epoch": 2.0,
        "loss/train_step": NaN,
        "acc/val": 0.9819999933242798,
        "loss/val": 0.07984623312950134,
        "acc/train_epoch": NaN,
        "loss/train_epoch": NaN,
        "acc/test": NaN,
        "loss/test": NaN
    },
    {
        "trainer/global_step": 422,
        "_step": 21,
        "_runtime": 175.221544866,
        "lr-SGD": NaN,
        "_timestamp": 1736358046.05607,
        "epoch": 2.0,
        "loss/train_step": NaN,
        "acc/val": NaN,
        "loss/val": NaN,
        "acc/train_epoch": 0.9837777614593506,
        "loss/train_epoch": 0.063381128013134,
        "acc/test": NaN,
        "loss/test": NaN
    },
    {
        "trainer/global_step": 449,
        "_step": 22,
        "_runtime": 181.031058125,
        "lr-SGD": 1e-05,
        "_timestamp": 1736358051.8653376,
        "epoch": NaN,
        "loss/train_step": NaN,
        "acc/val": NaN,
        "loss/val": NaN,
        "acc/train_epoch": NaN,
        "loss/train_epoch": NaN,
        "acc/test": NaN,
        "loss/test": NaN
    },
    {
        "trainer/global_step": 449,
        "_step": 23,
        "_runtime": 181.140263451,
        "lr-SGD": NaN,
        "_timestamp": 1736358051.9749572,
        "epoch": 3.0,
        "loss/train_step": 0.015262157656252384,
        "acc/val": NaN,
        "loss/val": NaN,
        "acc/train_epoch": NaN,
        "loss/train_epoch": NaN,
        "acc/test": NaN,
        "loss/test": NaN
    },
    {
        "trainer/global_step": 499,
        "_step": 24,
        "_runtime": 187.002625571,
        "lr-SGD": 1e-05,
        "_timestamp": 1736358057.8372679,
        "epoch": NaN,
        "loss/train_step": NaN,
        "acc/val": NaN,
        "loss/val": NaN,
        "acc/train_epoch": NaN,
        "loss/train_epoch": NaN,
        "acc/test": NaN,
        "loss/test": NaN
    },
    {
        "trainer/global_step": 499,
        "_step": 25,
        "_runtime": 187.113758029,
        "lr-SGD": NaN,
        "_timestamp": 1736358057.9479084,
        "epoch": 3.0,
        "loss/train_step": 0.05419875681400299,
        "acc/val": NaN,
        "loss/val": NaN,
        "acc/train_epoch": NaN,
        "loss/train_epoch": NaN,
        "acc/test": NaN,
        "loss/test": NaN
    },
    {
        "trainer/global_step": 549,
        "_step": 26,
        "_runtime": 192.996493183,
        "lr-SGD": 1e-05,
        "_timestamp": 1736358063.8310287,
        "epoch": NaN,
        "loss/train_step": NaN,
        "acc/val": NaN,
        "loss/val": NaN,
        "acc/train_epoch": NaN,
        "loss/train_epoch": NaN,
        "acc/test": NaN,
        "loss/test": NaN
    },
    {
        "trainer/global_step": 549,
        "_step": 27,
        "_runtime": 193.107120233,
        "lr-SGD": NaN,
        "_timestamp": 1736358063.9416518,
        "epoch": 3.0,
        "loss/train_step": 0.026344643905758858,
        "acc/val": NaN,
        "loss/val": NaN,
        "acc/train_epoch": NaN,
        "loss/train_epoch": NaN,
        "acc/test": NaN,
        "loss/test": NaN
    },
    {
        "trainer/global_step": 563,
        "_step": 28,
        "_runtime": 197.705027895,
        "lr-SGD": NaN,
        "_timestamp": 1736358068.5396512,
        "epoch": 3.0,
        "loss/train_step": NaN,
        "acc/val": 0.9760000109672546,
        "loss/val": 0.07748431712388992,
        "acc/train_epoch": NaN,
        "loss/train_epoch": NaN,
        "acc/test": NaN,
        "loss/test": NaN
    },
    {
        "trainer/global_step": 563,
        "_step": 29,
        "_runtime": 217.730231698,
        "lr-SGD": NaN,
        "_timestamp": 1736358088.5644321,
        "epoch": 3.0,
        "loss/train_step": NaN,
        "acc/val": NaN,
        "loss/val": NaN,
        "acc/train_epoch": 0.9844444394111633,
        "loss/train_epoch": 0.05879443883895874,
        "acc/test": NaN,
        "loss/test": NaN
    },
    {
        "trainer/global_step": 599,
        "_step": 30,
        "_runtime": 224.520941815,
        "lr-SGD": 1e-05,
        "_timestamp": 1736358095.3550682,
        "epoch": NaN,
        "loss/train_step": NaN,
        "acc/val": NaN,
        "loss/val": NaN,
        "acc/train_epoch": NaN,
        "loss/train_epoch": NaN,
        "acc/test": NaN,
        "loss/test": NaN
    },
    {
        "trainer/global_step": 599,
        "_step": 31,
        "_runtime": 224.631085148,
        "lr-SGD": NaN,
        "_timestamp": 1736358095.4656565,
        "epoch": 4.0,
        "loss/train_step": 0.02443511039018631,
        "acc/val": NaN,
        "loss/val": NaN,
        "acc/train_epoch": NaN,
        "loss/train_epoch": NaN,
        "acc/test": NaN,
        "loss/test": NaN
    },
    {
        "trainer/global_step": 649,
        "_step": 32,
        "_runtime": 230.531884735,
        "lr-SGD": 1e-05,
        "_timestamp": 1736358101.3665042,
        "epoch": NaN,
        "loss/train_step": NaN,
        "acc/val": NaN,
        "loss/val": NaN,
        "acc/train_epoch": NaN,
        "loss/train_epoch": NaN,
        "acc/test": NaN,
        "loss/test": NaN
    },
    {
        "trainer/global_step": 649,
        "_step": 33,
        "_runtime": 230.643080682,
        "lr-SGD": NaN,
        "_timestamp": 1736358101.4776895,
        "epoch": 4.0,
        "loss/train_step": 0.030673209577798843,
        "acc/val": NaN,
        "loss/val": NaN,
        "acc/train_epoch": NaN,
        "loss/train_epoch": NaN,
        "acc/test": NaN,
        "loss/test": NaN
    },
    {
        "trainer/global_step": 699,
        "_step": 34,
        "_runtime": 236.491245608,
        "lr-SGD": 1e-05,
        "_timestamp": 1736358107.3259604,
        "epoch": NaN,
        "loss/train_step": NaN,
        "acc/val": NaN,
        "loss/val": NaN,
        "acc/train_epoch": NaN,
        "loss/train_epoch": NaN,
        "acc/test": NaN,
        "loss/test": NaN
    },
    {
        "trainer/global_step": 699,
        "_step": 35,
        "_runtime": 236.6021142,
        "lr-SGD": NaN,
        "_timestamp": 1736358107.4365056,
        "epoch": 4.0,
        "loss/train_step": 0.039207011461257935,
        "acc/val": NaN,
        "loss/val": NaN,
        "acc/train_epoch": NaN,
        "loss/train_epoch": NaN,
        "acc/test": NaN,
        "loss/test": NaN
    },
    {
        "trainer/global_step": 704,
        "_step": 36,
        "_runtime": 239.966024502,
        "lr-SGD": NaN,
        "_timestamp": 1736358110.800577,
        "epoch": 4.0,
        "loss/train_step": NaN,
        "acc/val": 0.9819999933242798,
        "loss/val": 0.06765527278184891,
        "acc/train_epoch": NaN,
        "loss/train_epoch": NaN,
        "acc/test": NaN,
        "loss/test": NaN
    },
    {
        "trainer/global_step": 704,
        "_step": 37,
        "_runtime": 259.703840358,
        "lr-SGD": NaN,
        "_timestamp": 1736358130.538532,
        "epoch": 4.0,
        "loss/train_step": NaN,
        "acc/val": NaN,
        "loss/val": NaN,
        "acc/train_epoch": 0.9868888854980469,
        "loss/train_epoch": 0.05523110181093216,
        "acc/test": NaN,
        "loss/test": NaN
    },
    {
        "trainer/global_step": 749,
        "_step": 38,
        "_runtime": 267.361842609,
        "lr-SGD": 1e-05,
        "_timestamp": 1736358138.1964245,
        "epoch": NaN,
        "loss/train_step": NaN,
        "acc/val": NaN,
        "loss/val": NaN,
        "acc/train_epoch": NaN,
        "loss/train_epoch": NaN,
        "acc/test": NaN,
        "loss/test": NaN
    },
    {
        "trainer/global_step": 749,
        "_step": 39,
        "_runtime": 267.472250247,
        "lr-SGD": NaN,
        "_timestamp": 1736358138.3063364,
        "epoch": 5.0,
        "loss/train_step": 0.029925305396318436,
        "acc/val": NaN,
        "loss/val": NaN,
        "acc/train_epoch": NaN,
        "loss/train_epoch": NaN,
        "acc/test": NaN,
        "loss/test": NaN
    },
    {
        "trainer/global_step": 799,
        "_step": 40,
        "_runtime": 273.348856108,
        "lr-SGD": 1e-05,
        "_timestamp": 1736358144.1833625,
        "epoch": NaN,
        "loss/train_step": NaN,
        "acc/val": NaN,
        "loss/val": NaN,
        "acc/train_epoch": NaN,
        "loss/train_epoch": NaN,
        "acc/test": NaN,
        "loss/test": NaN
    },
    {
        "trainer/global_step": 799,
        "_step": 41,
        "_runtime": 273.461954458,
        "lr-SGD": NaN,
        "_timestamp": 1736358144.2962897,
        "epoch": 5.0,
        "loss/train_step": 0.018741397187113762,
        "acc/val": NaN,
        "loss/val": NaN,
        "acc/train_epoch": NaN,
        "loss/train_epoch": NaN,
        "acc/test": NaN,
        "loss/test": NaN
    },
    {
        "trainer/global_step": 845,
        "_step": 42,
        "_runtime": 281.92397919,
        "lr-SGD": NaN,
        "_timestamp": 1736358152.7583537,
        "epoch": 5.0,
        "loss/train_step": NaN,
        "acc/val": 0.9800000190734863,
        "loss/val": 0.0688592940568924,
        "acc/train_epoch": NaN,
        "loss/train_epoch": NaN,
        "acc/test": NaN,
        "loss/test": NaN
    },
    {
        "trainer/global_step": 845,
        "_step": 43,
        "_runtime": 302.333306361,
        "lr-SGD": NaN,
        "_timestamp": 1736358173.1680546,
        "epoch": 5.0,
        "loss/train_step": NaN,
        "acc/val": NaN,
        "loss/val": NaN,
        "acc/train_epoch": 0.9886666536331177,
        "loss/train_epoch": 0.051947928965091705,
        "acc/test": NaN,
        "loss/test": NaN
    },
    {
        "trainer/global_step": 846,
        "_step": 44,
        "_runtime": 307.715636787,
        "lr-SGD": NaN,
        "_timestamp": 1736358178.5501847,
        "epoch": 6.0,
        "loss/train_step": NaN,
        "acc/val": NaN,
        "loss/val": NaN,
        "acc/train_epoch": NaN,
        "loss/train_epoch": NaN,
        "acc/test": 0.984000027179718,
        "loss/test": 0.07446630299091339
    }
]