[
    {
        "trainer/global_step": 0,
        "_step": 0,
        "_runtime": 29.822494655,
        "lr": 5.000000058430487e-08,
        "elapsed_train_steps": 1.0,
        "epoch": 0,
        "loss/train_step": 2.0091629028320312,
        "_timestamp": 1736751167.954269,
        "acc/val": NaN,
        "loss/val": NaN,
        "acc/train_epoch": NaN,
        "loss/train_epoch": NaN,
        "acc/test": NaN,
        "loss/test": NaN
    },
    {
        "trainer/global_step": 1,
        "_step": 1,
        "_runtime": 30.274741886,
        "lr": 1.0000000116860974e-07,
        "elapsed_train_steps": 2.0,
        "epoch": 0,
        "loss/train_step": 2.130608558654785,
        "_timestamp": 1736751168.4066439,
        "acc/val": NaN,
        "loss/val": NaN,
        "acc/train_epoch": NaN,
        "loss/train_epoch": NaN,
        "acc/test": NaN,
        "loss/test": NaN
    },
    {
        "trainer/global_step": 2,
        "_step": 2,
        "_runtime": 30.727275752,
        "lr": 1.500000053056283e-07,
        "elapsed_train_steps": 3.0,
        "epoch": 0,
        "loss/train_step": 2.2389543056488037,
        "_timestamp": 1736751168.8589294,
        "acc/val": NaN,
        "loss/val": NaN,
        "acc/train_epoch": NaN,
        "loss/train_epoch": NaN,
        "acc/test": NaN,
        "loss/test": NaN
    },
    {
        "trainer/global_step": 3,
        "_step": 3,
        "_runtime": 31.180533232,
        "lr": 2.0000000233721948e-07,
        "elapsed_train_steps": 4.0,
        "epoch": 0,
        "loss/train_step": 1.8426717519760132,
        "_timestamp": 1736751169.3123982,
        "acc/val": NaN,
        "loss/val": NaN,
        "acc/train_epoch": NaN,
        "loss/train_epoch": NaN,
        "acc/test": NaN,
        "loss/test": NaN
    },
    {
        "trainer/global_step": 4,
        "_step": 4,
        "_runtime": 31.636261909,
        "lr": 2.499999993688107e-07,
        "elapsed_train_steps": 5.0,
        "epoch": 0,
        "loss/train_step": 2.1872406005859375,
        "_timestamp": 1736751169.7680905,
        "acc/val": NaN,
        "loss/val": NaN,
        "acc/train_epoch": NaN,
        "loss/train_epoch": NaN,
        "acc/test": NaN,
        "loss/test": NaN
    },
    {
        "trainer/global_step": 5,
        "_step": 5,
        "_runtime": 32.089123451,
        "lr": 3.000000106112566e-07,
        "elapsed_train_steps": 6.0,
        "epoch": 0,
        "loss/train_step": 2.0858066082000732,
        "_timestamp": 1736751170.2210119,
        "acc/val": NaN,
        "loss/val": NaN,
        "acc/train_epoch": NaN,
        "loss/train_epoch": NaN,
        "acc/test": NaN,
        "loss/test": NaN
    },
    {
        "trainer/global_step": 6,
        "_step": 6,
        "_runtime": 32.541374054,
        "lr": 3.4999999343199306e-07,
        "elapsed_train_steps": 7.0,
        "epoch": 0,
        "loss/train_step": 1.7742280960083008,
        "_timestamp": 1736751170.6732326,
        "acc/val": NaN,
        "loss/val": NaN,
        "acc/train_epoch": NaN,
        "loss/train_epoch": NaN,
        "acc/test": NaN,
        "loss/test": NaN
    },
    {
        "trainer/global_step": 7,
        "_step": 7,
        "_runtime": 32.993763337,
        "lr": 4.0000000467443897e-07,
        "elapsed_train_steps": 8.0,
        "epoch": 0,
        "loss/train_step": 2.11810302734375,
        "_timestamp": 1736751171.1255784,
        "acc/val": NaN,
        "loss/val": NaN,
        "acc/train_epoch": NaN,
        "loss/train_epoch": NaN,
        "acc/test": NaN,
        "loss/test": NaN
    },
    {
        "trainer/global_step": 8,
        "_step": 8,
        "_runtime": 33.445922382,
        "lr": 4.4999998749517545e-07,
        "elapsed_train_steps": 9.0,
        "epoch": 0,
        "loss/train_step": 2.359287977218628,
        "_timestamp": 1736751171.577827,
        "acc/val": NaN,
        "loss/val": NaN,
        "acc/train_epoch": NaN,
        "loss/train_epoch": NaN,
        "acc/test": NaN,
        "loss/test": NaN
    },
    {
        "trainer/global_step": 9,
        "_step": 9,
        "_runtime": 33.898303942,
        "lr": 4.999999987376214e-07,
        "elapsed_train_steps": 10.0,
        "epoch": 0,
        "loss/train_step": 1.8949542045593262,
        "_timestamp": 1736751172.0301619,
        "acc/val": NaN,
        "loss/val": NaN,
        "acc/train_epoch": NaN,
        "loss/train_epoch": NaN,
        "acc/test": NaN,
        "loss/test": NaN
    },
    {
        "trainer/global_step": 10,
        "_step": 10,
        "_runtime": 34.350798026,
        "lr": 5.499999815583578e-07,
        "elapsed_train_steps": 11.0,
        "epoch": 0,
        "loss/train_step": 1.9538875818252563,
        "_timestamp": 1736751172.4827254,
        "acc/val": NaN,
        "loss/val": NaN,
        "acc/train_epoch": NaN,
        "loss/train_epoch": NaN,
        "acc/test": NaN,
        "loss/test": NaN
    },
    {
        "trainer/global_step": 11,
        "_step": 11,
        "_runtime": 34.803681327,
        "lr": 6.000000212225132e-07,
        "elapsed_train_steps": 12.0,
        "epoch": 0,
        "loss/train_step": 1.8488044738769531,
        "_timestamp": 1736751172.9352815,
        "acc/val": NaN,
        "loss/val": NaN,
        "acc/train_epoch": NaN,
        "loss/train_epoch": NaN,
        "acc/test": NaN,
        "loss/test": NaN
    },
    {
        "trainer/global_step": 12,
        "_step": 12,
        "_runtime": 35.255433637,
        "lr": 6.500000040432496e-07,
        "elapsed_train_steps": 13.0,
        "epoch": 0,
        "loss/train_step": 2.135674238204956,
        "_timestamp": 1736751173.3873196,
        "acc/val": NaN,
        "loss/val": NaN,
        "acc/train_epoch": NaN,
        "loss/train_epoch": NaN,
        "acc/test": NaN,
        "loss/test": NaN
    },
    {
        "trainer/global_step": 13,
        "_step": 13,
        "_runtime": 35.708727257,
        "lr": 6.999999868639861e-07,
        "elapsed_train_steps": 14.0,
        "epoch": 0,
        "loss/train_step": 1.83968985080719,
        "_timestamp": 1736751173.8405466,
        "acc/val": NaN,
        "loss/val": NaN,
        "acc/train_epoch": NaN,
        "loss/train_epoch": NaN,
        "acc/test": NaN,
        "loss/test": NaN
    },
    {
        "trainer/global_step": 14,
        "_step": 14,
        "_runtime": 36.160867253,
        "lr": 7.500000265281415e-07,
        "elapsed_train_steps": 15.0,
        "epoch": 0,
        "loss/train_step": 1.9021061658859253,
        "_timestamp": 1736751174.2927725,
        "acc/val": NaN,
        "loss/val": NaN,
        "acc/train_epoch": NaN,
        "loss/train_epoch": NaN,
        "acc/test": NaN,
        "loss/test": NaN
    },
    {
        "trainer/global_step": 15,
        "_step": 15,
        "_runtime": 36.613362635,
        "lr": 8.000000093488779e-07,
        "elapsed_train_steps": 16.0,
        "epoch": 0,
        "loss/train_step": 2.007342576980591,
        "_timestamp": 1736751174.7452044,
        "acc/val": NaN,
        "loss/val": NaN,
        "acc/train_epoch": NaN,
        "loss/train_epoch": NaN,
        "acc/test": NaN,
        "loss/test": NaN
    },
    {
        "trainer/global_step": 16,
        "_step": 16,
        "_runtime": 37.07076858,
        "lr": 8.499999921696144e-07,
        "elapsed_train_steps": 17.0,
        "epoch": 0,
        "loss/train_step": 1.9148110151290894,
        "_timestamp": 1736751175.202676,
        "acc/val": NaN,
        "loss/val": NaN,
        "acc/train_epoch": NaN,
        "loss/train_epoch": NaN,
        "acc/test": NaN,
        "loss/test": NaN
    },
    {
        "trainer/global_step": 17,
        "_step": 17,
        "_runtime": 37.527012256,
        "lr": 8.999999749903509e-07,
        "elapsed_train_steps": 18.0,
        "epoch": 0,
        "loss/train_step": 2.1696555614471436,
        "_timestamp": 1736751175.6588905,
        "acc/val": NaN,
        "loss/val": NaN,
        "acc/train_epoch": NaN,
        "loss/train_epoch": NaN,
        "acc/test": NaN,
        "loss/test": NaN
    },
    {
        "trainer/global_step": 18,
        "_step": 18,
        "_runtime": 37.980755041,
        "lr": 9.500000146545062e-07,
        "elapsed_train_steps": 19.0,
        "epoch": 0,
        "loss/train_step": 1.7415271997451782,
        "_timestamp": 1736751176.1126554,
        "acc/val": NaN,
        "loss/val": NaN,
        "acc/train_epoch": NaN,
        "loss/train_epoch": NaN,
        "acc/test": NaN,
        "loss/test": NaN
    },
    {
        "trainer/global_step": 19,
        "_step": 19,
        "_runtime": 38.433210304,
        "lr": 9.999999974752427e-07,
        "elapsed_train_steps": 20.0,
        "epoch": 0,
        "loss/train_step": 1.7328739166259766,
        "_timestamp": 1736751176.5651195,
        "acc/val": NaN,
        "loss/val": NaN,
        "acc/train_epoch": NaN,
        "loss/train_epoch": NaN,
        "acc/test": NaN,
        "loss/test": NaN
    },
    {
        "trainer/global_step": 20,
        "_step": 20,
        "_runtime": 38.885665315,
        "lr": 1.050000037139398e-06,
        "elapsed_train_steps": 21.0,
        "epoch": 0,
        "loss/train_step": 1.783833622932434,
        "_timestamp": 1736751177.0175278,
        "acc/val": NaN,
        "loss/val": NaN,
        "acc/train_epoch": NaN,
        "loss/train_epoch": NaN,
        "acc/test": NaN,
        "loss/test": NaN
    },
    {
        "trainer/global_step": 21,
        "_step": 21,
        "_runtime": 39.337981872,
        "lr": 1.0999999631167157e-06,
        "elapsed_train_steps": 22.0,
        "epoch": 0,
        "loss/train_step": 1.909210443496704,
        "_timestamp": 1736751177.4697273,
        "acc/val": NaN,
        "loss/val": NaN,
        "acc/train_epoch": NaN,
        "loss/train_epoch": NaN,
        "acc/test": NaN,
        "loss/test": NaN
    },
    {
        "trainer/global_step": 22,
        "_step": 22,
        "_runtime": 39.789896176,
        "lr": 1.150000002780871e-06,
        "elapsed_train_steps": 23.0,
        "epoch": 0,
        "loss/train_step": 1.8691513538360596,
        "_timestamp": 1736751177.9217238,
        "acc/val": NaN,
        "loss/val": NaN,
        "acc/train_epoch": NaN,
        "loss/train_epoch": NaN,
        "acc/test": NaN,
        "loss/test": NaN
    },
    {
        "trainer/global_step": 23,
        "_step": 23,
        "_runtime": 40.242115463,
        "lr": 1.2000000424450263e-06,
        "elapsed_train_steps": 24.0,
        "epoch": 0,
        "loss/train_step": 1.6990382671356201,
        "_timestamp": 1736751178.3738756,
        "acc/val": NaN,
        "loss/val": NaN,
        "acc/train_epoch": NaN,
        "loss/train_epoch": NaN,
        "acc/test": NaN,
        "loss/test": NaN
    },
    {
        "trainer/global_step": 24,
        "_step": 24,
        "_runtime": 40.694330973,
        "lr": 1.249999968422344e-06,
        "elapsed_train_steps": 25.0,
        "epoch": 0,
        "loss/train_step": 1.8736807107925415,
        "_timestamp": 1736751178.8261993,
        "acc/val": NaN,
        "loss/val": NaN,
        "acc/train_epoch": NaN,
        "loss/train_epoch": NaN,
        "acc/test": NaN,
        "loss/test": NaN
    },
    {
        "trainer/global_step": 25,
        "_step": 25,
        "_runtime": 41.147445484,
        "lr": 1.3000000080864993e-06,
        "elapsed_train_steps": 26.0,
        "epoch": 0,
        "loss/train_step": 1.76854407787323,
        "_timestamp": 1736751179.2793667,
        "acc/val": NaN,
        "loss/val": NaN,
        "acc/train_epoch": NaN,
        "loss/train_epoch": NaN,
        "acc/test": NaN,
        "loss/test": NaN
    },
    {
        "trainer/global_step": 26,
        "_step": 26,
        "_runtime": 41.599875428,
        "lr": 1.3500000477506546e-06,
        "elapsed_train_steps": 27.0,
        "epoch": 0,
        "loss/train_step": 1.6431742906570435,
        "_timestamp": 1736751179.731737,
        "acc/val": NaN,
        "loss/val": NaN,
        "acc/train_epoch": NaN,
        "loss/train_epoch": NaN,
        "acc/test": NaN,
        "loss/test": NaN
    },
    {
        "trainer/global_step": 27,
        "_step": 27,
        "_runtime": 42.052005482,
        "lr": 1.3999999737279722e-06,
        "elapsed_train_steps": 28.0,
        "epoch": 0,
        "loss/train_step": 1.9887721538543701,
        "_timestamp": 1736751180.183918,
        "acc/val": NaN,
        "loss/val": NaN,
        "acc/train_epoch": NaN,
        "loss/train_epoch": NaN,
        "acc/test": NaN,
        "loss/test": NaN
    },
    {
        "trainer/global_step": 28,
        "_step": 28,
        "_runtime": 42.504242819,
        "lr": 1.4500000133921276e-06,
        "elapsed_train_steps": 29.0,
        "epoch": 0,
        "loss/train_step": 1.8748478889465332,
        "_timestamp": 1736751180.6361535,
        "acc/val": NaN,
        "loss/val": NaN,
        "acc/train_epoch": NaN,
        "loss/train_epoch": NaN,
        "acc/test": NaN,
        "loss/test": NaN
    },
    {
        "trainer/global_step": 29,
        "_step": 29,
        "_runtime": 42.956833536,
        "lr": 1.500000053056283e-06,
        "elapsed_train_steps": 30.0,
        "epoch": 0,
        "loss/train_step": 1.7039650678634644,
        "_timestamp": 1736751181.0887194,
        "acc/val": NaN,
        "loss/val": NaN,
        "acc/train_epoch": NaN,
        "loss/train_epoch": NaN,
        "acc/test": NaN,
        "loss/test": NaN
    },
    {
        "trainer/global_step": 30,
        "_step": 30,
        "_runtime": 43.409331953,
        "lr": 1.5499999790336005e-06,
        "elapsed_train_steps": 31.0,
        "epoch": 0,
        "loss/train_step": 1.6013710498809814,
        "_timestamp": 1736751181.5412343,
        "acc/val": NaN,
        "loss/val": NaN,
        "acc/train_epoch": NaN,
        "loss/train_epoch": NaN,
        "acc/test": NaN,
        "loss/test": NaN
    },
    {
        "trainer/global_step": 31,
        "_step": 31,
        "_runtime": 43.744824974,
        "lr": 1.6000000186977559e-06,
        "elapsed_train_steps": 32.0,
        "epoch": 0,
        "loss/train_step": 1.698905348777771,
        "_timestamp": 1736751181.8767128,
        "acc/val": NaN,
        "loss/val": NaN,
        "acc/train_epoch": NaN,
        "loss/train_epoch": NaN,
        "acc/test": NaN,
        "loss/test": NaN
    },
    {
        "trainer/global_step": 31,
        "_step": 32,
        "_runtime": 46.269081878,
        "lr": NaN,
        "elapsed_train_steps": NaN,
        "epoch": 0,
        "loss/train_step": NaN,
        "_timestamp": 1736751184.400896,
        "acc/val": 0.5764966607093811,
        "loss/val": 1.5919550657272339,
        "acc/train_epoch": NaN,
        "loss/train_epoch": NaN,
        "acc/test": NaN,
        "loss/test": NaN
    },
    {
        "trainer/global_step": 31,
        "_step": 33,
        "_runtime": 46.279909544,
        "lr": NaN,
        "elapsed_train_steps": NaN,
        "epoch": 0,
        "loss/train_step": NaN,
        "_timestamp": 1736751184.4118645,
        "acc/val": NaN,
        "loss/val": NaN,
        "acc/train_epoch": 0.4796847999095917,
        "loss/train_epoch": 1.91755211353302,
        "acc/test": NaN,
        "loss/test": NaN
    },
    {
        "trainer/global_step": 32,
        "_step": 34,
        "_runtime": 51.34347791,
        "lr": NaN,
        "elapsed_train_steps": NaN,
        "epoch": 1,
        "loss/train_step": NaN,
        "_timestamp": 1736751189.4752932,
        "acc/val": NaN,
        "loss/val": NaN,
        "acc/train_epoch": NaN,
        "loss/train_epoch": NaN,
        "acc/test": 0.5831485390663147,
        "loss/test": 1.5875440835952759
    }
]